thorn/__init__.py
thorn/_state.py
thorn/app.py
thorn/conf.py
thorn/decorators.py
thorn/events.py
thorn/exceptions.py
thorn/request.py
thorn/reverse.py
thorn/tasks.py
thorn/validators.py
thorn/dispatch/__init__.py
thorn/dispatch/base.py
thorn/dispatch/celery.py
thorn/dispatch/disabled.py
thorn/django/__init__.py
thorn/django/admin.py
thorn/django/apps.py
thorn/django/managers.py
thorn/django/models.py
thorn/django/signals.py
thorn/django/tasks.py
thorn/django/utils.py
thorn/django/migrations/0001_initial.py
thorn/django/migrations/0002_auto_20160523_1905.py
thorn/django/migrations/__init__.py
thorn/django/rest_framework/__init__.py
thorn/django/rest_framework/serializers.py
thorn/django/rest_framework/urls.py
thorn/django/rest_framework/views.py
thorn/environment/__init__.py
thorn/environment/django.py
thorn/funtests/__init__.py
thorn/funtests/base.py
thorn/funtests/celery.py
thorn/funtests/suite.py
thorn/funtests/tasks.py
thorn/generic/__init__.py
thorn/generic/models.py
thorn/generic/signals.py
thorn/utils/__init__.py
thorn/utils/compat.py
thorn/utils/functional.py
thorn/utils/hmac.py
thorn/utils/json.py
thorn/utils/log.py
thorn/utils/django/__init__.py
thorn/utils/django/query_utils.py
thorn/utils/django/tree.py
thorn-1.5.2.dist-info/DESCRIPTION.rst
thorn-1.5.2.dist-info/METADATA
thorn-1.5.2.dist-info/RECORD
thorn-1.5.2.dist-info/WHEEL
thorn-1.5.2.dist-info/metadata.json
thorn-1.5.2.dist-info/top_level.txt
