Metadata-Version: 1.1
Name: thorn
Version: 1.5.2
Summary: Python Webhook and Event Framework.
Home-page: http://github.com/robinhood/thorn
Author: Robinhood Markets
Author-email: thorn@robinhood.com
License: BSD
Platform: any
Classifier: Development Status :: 4 - Beta
Classifier: Programming Language :: Python
Classifier: Programming Language :: Python :: 2
Classifier: Programming Language :: Python :: 2.7
Classifier: Programming Language :: Python :: 3
Classifier: Programming Language :: Python :: 3.4
Classifier: Programming Language :: Python :: 3.5
Classifier: Framework :: Django :: 1.8
Classifier: Framework :: Django :: 1.9
Classifier: License :: OSI Approved :: BSD License
Classifier: Intended Audience :: Developers
Classifier: Operating System :: OS Independent
